agSwatch/__init__.py
agSwatch/agSwatch.py
agSwatch-1.0.0.0.dist-info/METADATA
agSwatch-1.0.0.0.dist-info/WHEEL
agSwatch-1.0.0.0.dist-info/top_level.txt
agSwatch-1.0.0.0.dist-info/RECORD
