Metadata-Version: 2.1
Name: agSwatch
Version: 1.0.0.0
Summary: Gestion de temporizadores
Home-page: https://agfra.es/
Author: Sdaroca
Author-email: sdaroca@agfra.com
License: MIT
